gsiberror/__init__.py
gsiberror/plot_functions.py
GSIBerror-1.1.0.dist-info/LICENSE
GSIBerror-1.1.0.dist-info/METADATA
GSIBerror-1.1.0.dist-info/WHEEL
GSIBerror-1.1.0.dist-info/top_level.txt
GSIBerror-1.1.0.dist-info/RECORD
